LICENSE
MANIFEST.in
README.md
pyproject.toml
setup.py
native/ccpf_cython.c
native/ccpf_cython.pyx
native/ccpf/ccpf.c
native/ccpf/ccpf.h
src/ccpf/__init__.py
src/ccpf.egg-info/PKG-INFO
src/ccpf.egg-info/SOURCES.txt
src/ccpf.egg-info/dependency_links.txt
src/ccpf.egg-info/top_level.txt
tests/test_basic.py