Metadata-Version: 2.1
Name: ccpf
Version: 1.0.0
Summary: CPF validation, generation and masking
Author-email: felipeasimos <felipe.asimos@gmail.com>
License: MIT
Keywords: cpf,validation,generation,mask
Classifier: Development Status :: 1 - Planning
Classifier: Intended Audience :: Developers
Classifier: Programming Language :: Python :: 3
Classifier: Programming Language :: C
Classifier: Operating System :: OS Independent
Classifier: License :: OSI Approved :: MIT License
Classifier: Topic :: Software Development :: Libraries :: Python Modules
Requires-Python: >=3.10
License-File: LICENSE
